wvflib/__init__.py
wvflib/base.py
wvflib/geometry.py
wvflib/groups.py
wvflib/material.py
wvflib-0.0.2.dist-info/DESCRIPTION.rst
wvflib-0.0.2.dist-info/METADATA
wvflib-0.0.2.dist-info/RECORD
wvflib-0.0.2.dist-info/WHEEL
wvflib-0.0.2.dist-info/metadata.json
wvflib-0.0.2.dist-info/top_level.txt
